rhesis/__init__.py
rhesis/py.typed
rhesis/sdk/__init__.py
rhesis/sdk/cli.py
rhesis/sdk/config.py
rhesis/sdk/enums.py
rhesis/sdk/errors.py
rhesis/sdk/utils.py
rhesis/sdk/clients/__init__.py
rhesis/sdk/clients/api.py
rhesis/sdk/clients/rhesis.py
rhesis/sdk/connector/__init__.py
rhesis/sdk/connector/connection.py
rhesis/sdk/connector/executor.py
rhesis/sdk/connector/manager.py
rhesis/sdk/connector/registry.py
rhesis/sdk/connector/schemas.py
rhesis/sdk/connector/serializer.py
rhesis/sdk/connector/types.py
rhesis/sdk/decorators/__init__.py
rhesis/sdk/decorators/_state.py
rhesis/sdk/decorators/builders.py
rhesis/sdk/decorators/endpoint.py
rhesis/sdk/decorators/observe.py
rhesis/sdk/entities/__init__.py
rhesis/sdk/entities/base_collection.py
rhesis/sdk/entities/base_entity.py
rhesis/sdk/entities/behavior.py
rhesis/sdk/entities/category.py
rhesis/sdk/entities/endpoint.py
rhesis/sdk/entities/model.py
rhesis/sdk/entities/project.py
rhesis/sdk/entities/prompt.py
rhesis/sdk/entities/status.py
rhesis/sdk/entities/test.py
rhesis/sdk/entities/test_configuration.py
rhesis/sdk/entities/test_result.py
rhesis/sdk/entities/test_run.py
rhesis/sdk/entities/test_set.py
rhesis/sdk/entities/topic.py
rhesis/sdk/metrics/__init__.py
rhesis/sdk/metrics/base.py
rhesis/sdk/metrics/constants.py
rhesis/sdk/metrics/factory.py
rhesis/sdk/metrics/utils.py
rhesis/sdk/metrics/config/__init__.py
rhesis/sdk/metrics/config/backends.yml
rhesis/sdk/metrics/config/defaults.yml
rhesis/sdk/metrics/config/loader.py
rhesis/sdk/metrics/conversational/__init__.py
rhesis/sdk/metrics/conversational/base.py
rhesis/sdk/metrics/conversational/types.py
rhesis/sdk/metrics/providers/__init__.py
rhesis/sdk/metrics/providers/deepeval/__init__.py
rhesis/sdk/metrics/providers/deepeval/conversational_base.py
rhesis/sdk/metrics/providers/deepeval/conversational_metrics.py
rhesis/sdk/metrics/providers/deepeval/factory.py
rhesis/sdk/metrics/providers/deepeval/metric_base.py
rhesis/sdk/metrics/providers/deepeval/metrics.py
rhesis_sdk-0.6.2.dist-info/METADATA
rhesis_sdk-0.6.2.dist-info/WHEEL
rhesis_sdk-0.6.2.dist-info/licenses/LICENSE
rhesis_sdk-0.6.2.dist-info/RECORD
