Metadata-Version: 2.4
Name: rhesis-sdk
Version: 0.6.2
Summary: SDK for testing and validating LLM applications
Project-URL: Homepage, https://rhesis.ai
Project-URL: Repository, https://github.com/rhesis-ai/rhesis
Project-URL: Documentation, https://rhesis-sdk.readthedocs.io
Project-URL: Bug Tracker, https://github.com/rhesis-ai/rhesis/issues
Author-email: Engineering Team <engineering@rhesis.ai>, Harry Cruz <harry@rhesis.ai>, Nicolai Bohn <nicolai@rhesis.ai>
License: MIT
License-File: LICENSE
Keywords: ai,llm,machine-learning,testing
Classifier: Development Status :: 4 - Beta
Classifier: Intended Audience :: Developers
Classifier: License :: OSI Approved :: MIT License
Classifier: Programming Language :: Python :: 3
Classifier: Programming Language :: Python :: 3.10
Classifier: Topic :: Software Development :: Libraries :: Python Modules
Classifier: Topic :: Software Development :: Testing
Requires-Python: >=3.10
Requires-Dist: deepeval==3.7.0
Requires-Dist: deepteam>=0.2.5
Requires-Dist: ipykernel>=7.1.0
Requires-Dist: ipython>=8.37.0
Requires-Dist: jinja2>=3.1.6
Requires-Dist: langchain-google-genai>=2.1.12
Requires-Dist: litellm>=1.76.0
Requires-Dist: markitdown[docx,pdf,pptx,xlsx]>=0.1.0
Requires-Dist: mcp>=1.2.0
Requires-Dist: opentelemetry-api>=1.32.1
Requires-Dist: opentelemetry-exporter-otlp-proto-http>=1.32.1
Requires-Dist: opentelemetry-sdk>=1.32.1
Requires-Dist: pandas>=2.2.2
Requires-Dist: pydantic>=2.0.0
Requires-Dist: python-dotenv>=1.0.1
Requires-Dist: pyyaml>=6.0
Requires-Dist: ragas>=0.3.7
Requires-Dist: requests>=2.31.0
Requires-Dist: tenacity>=8.2.3
Requires-Dist: tiktoken>=0.9.0
Requires-Dist: tqdm>=4.67.1
Requires-Dist: websockets>=12.0
Provides-Extra: all
Requires-Dist: accelerate>=1.2.0; extra == 'all'
Requires-Dist: bitsandbytes>=0.45.0; extra == 'all'
Requires-Dist: langchain-core>=1.2.5; extra == 'all'
Requires-Dist: langchain>=0.1.0; extra == 'all'
Requires-Dist: langgraph>=0.0.26; extra == 'all'
Requires-Dist: pyautogen>=0.2.0; extra == 'all'
Requires-Dist: torch>=2.8.0; extra == 'all'
Requires-Dist: transformers==4.57.1; extra == 'all'
Provides-Extra: all-integrations
Requires-Dist: langchain-core>=1.2.5; extra == 'all-integrations'
Requires-Dist: langchain>=0.1.0; extra == 'all-integrations'
Requires-Dist: langgraph>=0.0.26; extra == 'all-integrations'
Requires-Dist: pyautogen>=0.2.0; extra == 'all-integrations'
Provides-Extra: autogen
Requires-Dist: pyautogen>=0.2.0; extra == 'autogen'
Provides-Extra: garak
Requires-Dist: garak>=0.9.0; extra == 'garak'
Provides-Extra: huggingface
Requires-Dist: accelerate>=1.2.0; extra == 'huggingface'
Requires-Dist: bitsandbytes>=0.45.0; extra == 'huggingface'
Requires-Dist: torch>=2.8.0; extra == 'huggingface'
Requires-Dist: transformers==4.57.1; extra == 'huggingface'
Provides-Extra: langchain
Requires-Dist: langchain-core>=1.2.5; extra == 'langchain'
Requires-Dist: langchain>=0.1.0; extra == 'langchain'
Provides-Extra: langgraph
Requires-Dist: langchain-core>=1.2.5; extra == 'langgraph'
Requires-Dist: langchain>=0.1.0; extra == 'langgraph'
Requires-Dist: langgraph>=0.0.26; extra == 'langgraph'
